{
  "hash": "957d5dcf",
  "configHash": "a3c915c1",
  "lockfileHash": "54eb7816",
  "browserHash": "eb063161",
  "optimized": {
    "react/jsx-dev-runtime": {
      "src": "../../node_modules/react/jsx-dev-runtime.js",
      "file": "react_jsx-dev-runtime.js",
      "fileHash": "b56390ef",
      "needsInterop": true
    },
    "react": {
      "src": "../../node_modules/react/index.js",
      "file": "react.js",
      "fileHash": "a36f7ffa",
      "needsInterop": true
    },
    "react-dom/client": {
      "src": "../../node_modules/react-dom/client.js",
      "file": "react-dom_client.js",
      "fileHash": "5abb9166",
      "needsInterop": true
    }
  },
  "chunks": {
    "chunk-BL66EYTC": {
      "file": "chunk-BL66EYTC.js"
    }
  }
}